<?xml version="1.0"?>
<question id="VB_42" module="VB">
  <questionText>Don wanted to find out if a battery powered toy truck would always travel the same distance in 10 seconds no matter how heavy a load the truck carried. He placed one or more blocks (the load) in the back of the truck and recorded his results. (Each block had the same mass.) The following graph displays his results. What is the relationship between the number of blocks and the distance traveled by the truck in 10 seconds?</questionText>
  <referenceAnswers>
    <referenceAnswer id="VB_42-a1" text="The more blocks the truck carries, the less distance the truck travels in 10 seconds.">
      <tokens>
        <token id="VB_42_ra1">The</token>
        <token id="VB_42_ra2">more</token>
        <token id="VB_42_ra3">blocks</token>
        <token id="VB_42_ra4">the</token>
        <token id="VB_42_ra5">truck</token>
        <token id="VB_42_ra6">carries</token>
        <token id="VB_42_ra7">,</token>
        <token id="VB_42_ra8">the</token>
        <token id="VB_42_ra9">less</token>
        <token id="VB_42_ra10">distance</token>
        <token id="VB_42_ra11">the</token>
        <token id="VB_42_ra12">truck</token>
        <token id="VB_42_ra13">travels</token>
        <token id="VB_42_ra14">in</token>
        <token id="VB_42_ra15">10</token>
        <token id="VB_42_ra16">seconds</token>
        <token id="VB_42_ra17">.</token>
      </tokens>
      <facets>
        <facet id="VB_42_f1" govNum="VB_42_ra6" modNum="VB_42_ra5" reltn="Means" govText="carries" isAssumed="true" modText="truck"/>
        <facet id="VB_42_f2" govNum="VB_42_ra6" modNum="VB_42_ra2" reltn="Theme" govText="carries" modText="more"/>
        <facet id="VB_42_f3" govNum="VB_42_ra2" modNum="VB_42_ra3" reltn="NMod" govText="more" modText="blocks"/>
        <facet id="VB_42_f4" govNum="VB_42_ra13" modNum="VB_42_ra12" reltn="Theme" govText="travels" isAssumed="true" modText="truck"/>
        <facet id="VB_42_f5" govNum="VB_42_ra13" modNum="VB_42_ra9" reltn="Extent" govText="travels" modText="less"/>
        <facet id="VB_42_f6" govNum="VB_42_ra9" modNum="VB_42_ra10" reltn="NMod" govText="less" modText="distance"/>
        <facet id="VB_42_f7" govNum="VB_42_ra13" modNum="VB_42_ra15" reltn="Time_in" govText="travels" isAssumed="true" modText="10"/>
        <facet id="VB_42_f8" govNum="VB_42_ra15" modNum="VB_42_ra16" reltn="NMod" govText="10" isAssumed="true" modText="seconds"/>
        <facet id="VB_42_f9" govNum="VB_42_ra13" modNum="VB_42_ra6" reltn="Cause_COMMA" childProp2Facet2="VB_42_f2" childProp1Facet1="VB_42_f4" govText="travels" childProp1Facet2="VB_42_f5" modText="carries" childProp2Facet1="VB_42_f1"/>
      </facets>
    </referenceAnswer>
  </referenceAnswers>
  <studentAnswers>
    <studentAnswer id="VB.42.381.1" answerText="As the number of blocks increases the distance decreases." accuracy="correct">
      <facetEntailment facetID="VB_42_f1" label="Assumed"/>
      <facetEntailment facetID="VB_42_f2" label="Inferred"/>
      <facetEntailment facetID="VB_42_f3" label="Expressed"/>
      <facetEntailment facetID="VB_42_f4" label="Assumed"/>
      <facetEntailment facetID="VB_42_f5" label="Expressed"/>
      <facetEntailment facetID="VB_42_f6" label="Expressed"/>
      <facetEntailment facetID="VB_42_f7" label="Assumed"/>
      <facetEntailment facetID="VB_42_f8" label="Assumed"/>
      <facetEntailment facetID="VB_42_f9" label="Expressed"/>
    </studentAnswer>
    <studentAnswer id="VB.42.384.1" answerText="As the blocks increase the distance decreases." accuracy="correct">
      <facetEntailment facetID="VB_42_f1" label="Assumed"/>
      <facetEntailment facetID="VB_42_f2" label="Inferred"/>
      <facetEntailment facetID="VB_42_f3" label="Expressed"/>
      <facetEntailment facetID="VB_42_f4" label="Assumed"/>
      <facetEntailment facetID="VB_42_f5" label="Expressed"/>
      <facetEntailment facetID="VB_42_f6" label="Expressed"/>
      <facetEntailment facetID="VB_42_f7" label="Assumed"/>
      <facetEntailment facetID="VB_42_f8" label="Assumed"/>
      <facetEntailment facetID="VB_42_f9" label="Expressed"/>
    </studentAnswer>
    <studentAnswer id="VB.42.394.1" answerText="The more blocks you put on the truck the farther it gets, in meters." accuracy="contradictory">
      <facetEntailment facetID="VB_42_f1" label="Expressed"/>
      <facetEntailment facetID="VB_42_f2" label="Expressed"/>
      <facetEntailment facetID="VB_42_f3" label="Expressed"/>
      <facetEntailment facetID="VB_42_f4" label="Expressed"/>
      <facetEntailment facetID="VB_42_f5" label="Contra-Expr"/>
      <facetEntailment facetID="VB_42_f6" label="Contra-Expr"/>
      <facetEntailment facetID="VB_42_f7" label="Assumed"/>
      <facetEntailment facetID="VB_42_f8" label="Assumed"/>
      <facetEntailment facetID="VB_42_f9" label="Expressed"/>
    </studentAnswer>
    <studentAnswer id="VB.42.401.1" answerText="As the number of blocks increases, the distance increase." accuracy="contradictory">
      <facetEntailment facetID="VB_42_f1" label="Assumed"/>
      <facetEntailment facetID="VB_42_f2" label="Unaddressed"/>
      <facetEntailment facetID="VB_42_f3" label="Expressed"/>
      <facetEntailment facetID="VB_42_f4" label="Assumed"/>
      <facetEntailment facetID="VB_42_f5" label="Unaddressed"/>
      <facetEntailment facetID="VB_42_f6" label="Contra-Expr"/>
      <facetEntailment facetID="VB_42_f7" label="Assumed"/>
      <facetEntailment facetID="VB_42_f8" label="Assumed"/>
      <facetEntailment facetID="VB_42_f9" label="Inferred"/>
    </studentAnswer>
    <studentAnswer id="VB.42.404.1" answerText="The relationship is as the number of blocks increases the distance decreases." accuracy="partially_correct_incomplete">
      <facetEntailment facetID="VB_42_f1" label="Assumed"/>
      <facetEntailment facetID="VB_42_f2" label="Inferred"/>
      <facetEntailment facetID="VB_42_f3" label="Expressed"/>
      <facetEntailment facetID="VB_42_f4" label="Expressed"/>
      <facetEntailment facetID="VB_42_f5" label="Unaddressed"/>
      <facetEntailment facetID="VB_42_f6" label="Expressed"/>
      <facetEntailment facetID="VB_42_f7" label="Assumed"/>
      <facetEntailment facetID="VB_42_f8" label="Assumed"/>
      <facetEntailment facetID="VB_42_f9" label="Inferred"/>
    </studentAnswer>
    <studentAnswer id="VB.42.406.1" answerText="The more blocks the shorter the distance traveled." accuracy="correct">
      <facetEntailment facetID="VB_42_f1" label="Assumed"/>
      <facetEntailment facetID="VB_42_f2" label="Inferred"/>
      <facetEntailment facetID="VB_42_f3" label="Expressed"/>
      <facetEntailment facetID="VB_42_f4" label="Assumed"/>
      <facetEntailment facetID="VB_42_f5" label="Expressed"/>
      <facetEntailment facetID="VB_42_f6" label="Expressed"/>
      <facetEntailment facetID="VB_42_f7" label="Assumed"/>
      <facetEntailment facetID="VB_42_f8" label="Assumed"/>
      <facetEntailment facetID="VB_42_f9" label="Inferred"/>
    </studentAnswer>
    <studentAnswer id="VB.42.416.1" answerText="Once he added one more the mass was slower and that is what he showed on the graph." accuracy="partially_correct_incomplete">
      <facetEntailment facetID="VB_42_f1" label="Assumed"/>
      <facetEntailment facetID="VB_42_f2" label="Inferred"/>
      <facetEntailment facetID="VB_42_f3" label="Inferred"/>
      <facetEntailment facetID="VB_42_f4" label="Assumed"/>
      <facetEntailment facetID="VB_42_f5" label="Diff-Arg"/>
      <facetEntailment facetID="VB_42_f6" label="Unaddressed"/>
      <facetEntailment facetID="VB_42_f7" label="Assumed"/>
      <facetEntailment facetID="VB_42_f8" label="Assumed"/>
      <facetEntailment facetID="VB_42_f9" label="Unaddressed"/>
    </studentAnswer>
    <studentAnswer id="VB.42.419.1" answerText="The distance goes up one every time also the number of blocks." accuracy="contradictory">
      <facetEntailment facetID="VB_42_f1" label="Assumed"/>
      <facetEntailment facetID="VB_42_f2" label="Inferred"/>
      <facetEntailment facetID="VB_42_f3" label="Expressed"/>
      <facetEntailment facetID="VB_42_f4" label="Assumed"/>
      <facetEntailment facetID="VB_42_f5" label="Contra-Expr"/>
      <facetEntailment facetID="VB_42_f6" label="Contra-Expr"/>
      <facetEntailment facetID="VB_42_f7" label="Assumed"/>
      <facetEntailment facetID="VB_42_f8" label="Assumed"/>
      <facetEntailment facetID="VB_42_f9" label="Unaddressed"/>
    </studentAnswer>
    <studentAnswer id="VB.42.423.1" answerText="It went farther with less blocks and it went no farther with more blocks." accuracy="contradictory">
      <facetEntailment facetID="VB_42_f1" label="Assumed"/>
      <facetEntailment facetID="VB_42_f2" label="Inferred"/>
      <facetEntailment facetID="VB_42_f3" label="Expressed"/>
      <facetEntailment facetID="VB_42_f4" label="Expressed"/>
      <facetEntailment facetID="VB_42_f5" label="Contra-Infr"/>
      <facetEntailment facetID="VB_42_f6" label="Contra-Infr"/>
      <facetEntailment facetID="VB_42_f7" label="Assumed"/>
      <facetEntailment facetID="VB_42_f8" label="Assumed"/>
      <facetEntailment facetID="VB_42_f9" label="Inferred"/>
    </studentAnswer>
    <studentAnswer id="VB.42.429.1" answerText="The relationship between the independent and the dependent variable is the more load the slower the truck will go." accuracy="partially_correct_incomplete">
      <facetEntailment facetID="VB_42_f1" label="Assumed"/>
      <facetEntailment facetID="VB_42_f2" label="Inferred"/>
      <facetEntailment facetID="VB_42_f3" label="Inferred"/>
      <facetEntailment facetID="VB_42_f4" label="Expressed"/>
      <facetEntailment facetID="VB_42_f5" label="Diff-Arg"/>
      <facetEntailment facetID="VB_42_f6" label="Unaddressed"/>
      <facetEntailment facetID="VB_42_f7" label="Assumed"/>
      <facetEntailment facetID="VB_42_f8" label="Assumed"/>
      <facetEntailment facetID="VB_42_f9" label="Inferred"/>
    </studentAnswer>
    <studentAnswer id="VB.42.432.1" answerText="One shows the number of blocks and one shows the distance of how far they went." accuracy="irrelevant">
      <facetEntailment facetID="VB_42_f1" label="Assumed"/>
      <facetEntailment facetID="VB_42_f2" label="Unaddressed"/>
      <facetEntailment facetID="VB_42_f3" label="Unaddressed"/>
      <facetEntailment facetID="VB_42_f4" label="Assumed"/>
      <facetEntailment facetID="VB_42_f5" label="Unaddressed"/>
      <facetEntailment facetID="VB_42_f6" label="Unaddressed"/>
      <facetEntailment facetID="VB_42_f7" label="Assumed"/>
      <facetEntailment facetID="VB_42_f8" label="Assumed"/>
      <facetEntailment facetID="VB_42_f9" label="Unaddressed"/>
    </studentAnswer>
    <studentAnswer id="VB.42.440.1" answerText="The more blocks the harder the truck tries to go faster causing it to go slower." accuracy="partially_correct_incomplete">
      <facetEntailment facetID="VB_42_f1" label="Assumed"/>
      <facetEntailment facetID="VB_42_f2" label="Inferred"/>
      <facetEntailment facetID="VB_42_f3" label="Expressed"/>
      <facetEntailment facetID="VB_42_f4" label="Expressed"/>
      <facetEntailment facetID="VB_42_f5" label="Diff-Arg"/>
      <facetEntailment facetID="VB_42_f6" label="Unaddressed"/>
      <facetEntailment facetID="VB_42_f7" label="Assumed"/>
      <facetEntailment facetID="VB_42_f8" label="Assumed"/>
      <facetEntailment facetID="VB_42_f9" label="Inferred"/>
    </studentAnswer>
    <studentAnswer id="VB.42.448.1" answerText="Every time he put a block in it went 5 meters shorter." accuracy="correct">
      <facetEntailment facetID="VB_42_f1" label="Expressed"/>
      <facetEntailment facetID="VB_42_f2" label="Inferred"/>
      <facetEntailment facetID="VB_42_f3" label="Inferred"/>
      <facetEntailment facetID="VB_42_f4" label="Expressed"/>
      <facetEntailment facetID="VB_42_f5" label="Expressed"/>
      <facetEntailment facetID="VB_42_f6" label="Inferred"/>
      <facetEntailment facetID="VB_42_f7" label="Assumed"/>
      <facetEntailment facetID="VB_42_f8" label="Assumed"/>
      <facetEntailment facetID="VB_42_f9" label="Expressed"/>
    </studentAnswer>
    <studentAnswer id="VB.42.452.1" answerText="The more the block, the less it goes, the less the blocks, the farther it goes." accuracy="correct">
      <facetEntailment facetID="VB_42_f1" label="Assumed"/>
      <facetEntailment facetID="VB_42_f2" label="Inferred"/>
      <facetEntailment facetID="VB_42_f3" label="Expressed"/>
      <facetEntailment facetID="VB_42_f4" label="Expressed"/>
      <facetEntailment facetID="VB_42_f5" label="Expressed"/>
      <facetEntailment facetID="VB_42_f6" label="Expressed"/>
      <facetEntailment facetID="VB_42_f7" label="Assumed"/>
      <facetEntailment facetID="VB_42_f8" label="Assumed"/>
      <facetEntailment facetID="VB_42_f9" label="Inferred"/>
    </studentAnswer>
    <studentAnswer id="VB.42.462.1" answerText="The relationship is it goes down one every time you add a block." accuracy="correct">
      <facetEntailment facetID="VB_42_f1" label="Assumed"/>
      <facetEntailment facetID="VB_42_f2" label="Inferred"/>
      <facetEntailment facetID="VB_42_f3" label="Expressed"/>
      <facetEntailment facetID="VB_42_f4" label="Assumed"/>
      <facetEntailment facetID="VB_42_f5" label="Inferred"/>
      <facetEntailment facetID="VB_42_f6" label="Inferred"/>
      <facetEntailment facetID="VB_42_f7" label="Assumed"/>
      <facetEntailment facetID="VB_42_f8" label="Assumed"/>
      <facetEntailment facetID="VB_42_f9" label="Inferred"/>
    </studentAnswer>
    <studentAnswer id="VB.42.466.1" answerText="The relationship between the number of blocks and the distance traveled by the truck in 10 seconds is that they both change how far the truck goes." accuracy="partially_correct_incomplete">
      <facetEntailment facetID="VB_42_f1" label="Assumed"/>
      <facetEntailment facetID="VB_42_f2" label="Inferred"/>
      <facetEntailment facetID="VB_42_f3" label="Inferred"/>
      <facetEntailment facetID="VB_42_f4" label="Expressed"/>
      <facetEntailment facetID="VB_42_f5" label="Unaddressed"/>
      <facetEntailment facetID="VB_42_f6" label="Unaddressed"/>
      <facetEntailment facetID="VB_42_f7" label="Expressed"/>
      <facetEntailment facetID="VB_42_f8" label="Expressed"/>
      <facetEntailment facetID="VB_42_f9" label="Unaddressed"/>
    </studentAnswer>
    <studentAnswer id="VB.42.475.1" answerText="The relationship is that the less blocks the toy truck has the more it will carry and the more blocks the less it can carry." accuracy="correct">
      <facetEntailment facetID="VB_42_f1" label="Expressed"/>
      <facetEntailment facetID="VB_42_f2" label="Expressed"/>
      <facetEntailment facetID="VB_42_f3" label="Expressed"/>
      <facetEntailment facetID="VB_42_f4" label="Assumed"/>
      <facetEntailment facetID="VB_42_f5" label="Inferred"/>
      <facetEntailment facetID="VB_42_f6" label="Inferred"/>
      <facetEntailment facetID="VB_42_f7" label="Assumed"/>
      <facetEntailment facetID="VB_42_f8" label="Assumed"/>
      <facetEntailment facetID="VB_42_f9" label="Inferred"/>
    </studentAnswer>
    <studentAnswer id="VB.42.477.1" answerText="The relationship between the number of blocks and the distance is that it decreases every time and all of it decreases together." accuracy="contradictory">
      <facetEntailment facetID="VB_42_f1" label="Assumed"/>
      <facetEntailment facetID="VB_42_f2" label="Contra-Infr"/>
      <facetEntailment facetID="VB_42_f3" label="Contra-Expr"/>
      <facetEntailment facetID="VB_42_f4" label="Assumed"/>
      <facetEntailment facetID="VB_42_f5" label="Inferred"/>
      <facetEntailment facetID="VB_42_f6" label="Expressed"/>
      <facetEntailment facetID="VB_42_f7" label="Assumed"/>
      <facetEntailment facetID="VB_42_f8" label="Assumed"/>
      <facetEntailment facetID="VB_42_f9" label="Inferred"/>
    </studentAnswer>
    <studentAnswer id="VB.42.481.1" answerText="The relationship is that the more blocks that you put in the truck the less distance it will cover." accuracy="correct">
      <facetEntailment facetID="VB_42_f1" label="Expressed"/>
      <facetEntailment facetID="VB_42_f2" label="Expressed"/>
      <facetEntailment facetID="VB_42_f3" label="Expressed"/>
      <facetEntailment facetID="VB_42_f4" label="Expressed"/>
      <facetEntailment facetID="VB_42_f5" label="Expressed"/>
      <facetEntailment facetID="VB_42_f6" label="Expressed"/>
      <facetEntailment facetID="VB_42_f7" label="Assumed"/>
      <facetEntailment facetID="VB_42_f8" label="Assumed"/>
      <facetEntailment facetID="VB_42_f9" label="Expressed"/>
    </studentAnswer>
    <studentAnswer id="VB.42.497.1" answerText="The more blocks he puts in the truck the less the truck will travel." accuracy="correct">
      <facetEntailment facetID="VB_42_f1" label="Expressed"/>
      <facetEntailment facetID="VB_42_f2" label="Expressed"/>
      <facetEntailment facetID="VB_42_f3" label="Expressed"/>
      <facetEntailment facetID="VB_42_f4" label="Expressed"/>
      <facetEntailment facetID="VB_42_f5" label="Expressed"/>
      <facetEntailment facetID="VB_42_f6" label="Expressed"/>
      <facetEntailment facetID="VB_42_f7" label="Assumed"/>
      <facetEntailment facetID="VB_42_f8" label="Assumed"/>
      <facetEntailment facetID="VB_42_f9" label="Expressed"/>
    </studentAnswer>
    <studentAnswer id="VB.42.501.1" answerText="That it is increasing by the matter of seconds." accuracy="irrelevant">
      <facetEntailment facetID="VB_42_f1" label="Assumed"/>
      <facetEntailment facetID="VB_42_f2" label="Unaddressed"/>
      <facetEntailment facetID="VB_42_f3" label="Unaddressed"/>
      <facetEntailment facetID="VB_42_f4" label="Assumed"/>
      <facetEntailment facetID="VB_42_f5" label="Unaddressed"/>
      <facetEntailment facetID="VB_42_f6" label="Unaddressed"/>
      <facetEntailment facetID="VB_42_f7" label="Assumed"/>
      <facetEntailment facetID="VB_42_f8" label="Assumed"/>
      <facetEntailment facetID="VB_42_f9" label="Unaddressed"/>
    </studentAnswer>
    <studentAnswer id="VB.42.503.1" answerText="The more number of blocks the less distance it goes or the less block the more distance." accuracy="correct">
      <facetEntailment facetID="VB_42_f1" label="Assumed"/>
      <facetEntailment facetID="VB_42_f2" label="Inferred"/>
      <facetEntailment facetID="VB_42_f3" label="Expressed"/>
      <facetEntailment facetID="VB_42_f4" label="Expressed"/>
      <facetEntailment facetID="VB_42_f5" label="Expressed"/>
      <facetEntailment facetID="VB_42_f6" label="Expressed"/>
      <facetEntailment facetID="VB_42_f7" label="Assumed"/>
      <facetEntailment facetID="VB_42_f8" label="Assumed"/>
      <facetEntailment facetID="VB_42_f9" label="Inferred"/>
    </studentAnswer>
    <studentAnswer id="VB.42.523.1" answerText="The number of blocks is measuring by meters." accuracy="irrelevant">
      <facetEntailment facetID="VB_42_f1" label="Assumed"/>
      <facetEntailment facetID="VB_42_f2" label="Unaddressed"/>
      <facetEntailment facetID="VB_42_f3" label="Unaddressed"/>
      <facetEntailment facetID="VB_42_f4" label="Assumed"/>
      <facetEntailment facetID="VB_42_f5" label="Unaddressed"/>
      <facetEntailment facetID="VB_42_f6" label="Unaddressed"/>
      <facetEntailment facetID="VB_42_f7" label="Assumed"/>
      <facetEntailment facetID="VB_42_f8" label="Assumed"/>
      <facetEntailment facetID="VB_42_f9" label="Unaddressed"/>
    </studentAnswer>
    <studentAnswer id="VB.42.530.1" answerText="If the truck has less blocks it goes further." accuracy="correct">
      <facetEntailment facetID="VB_42_f1" label="Expressed"/>
      <facetEntailment facetID="VB_42_f2" label="Expressed"/>
      <facetEntailment facetID="VB_42_f3" label="Inferred"/>
      <facetEntailment facetID="VB_42_f4" label="Expressed"/>
      <facetEntailment facetID="VB_42_f5" label="Inferred"/>
      <facetEntailment facetID="VB_42_f6" label="Inferred"/>
      <facetEntailment facetID="VB_42_f7" label="Assumed"/>
      <facetEntailment facetID="VB_42_f8" label="Assumed"/>
      <facetEntailment facetID="VB_42_f9" label="Expressed"/>
    </studentAnswer>
    <studentAnswer id="VB.42.533.1" answerText="The more blocks you add the less distance it would go. It would have more mass." accuracy="correct">
      <facetEntailment facetID="VB_42_f1" label="Assumed"/>
      <facetEntailment facetID="VB_42_f2" label="Expressed"/>
      <facetEntailment facetID="VB_42_f3" label="Expressed"/>
      <facetEntailment facetID="VB_42_f4" label="Expressed"/>
      <facetEntailment facetID="VB_42_f5" label="Expressed"/>
      <facetEntailment facetID="VB_42_f6" label="Expressed"/>
      <facetEntailment facetID="VB_42_f7" label="Assumed"/>
      <facetEntailment facetID="VB_42_f8" label="Assumed"/>
      <facetEntailment facetID="VB_42_f9" label="Expressed"/>
    </studentAnswer>
    <studentAnswer id="VB.42.535.1" answerText="The more blocks Don added the slower the toy truck will go." accuracy="partially_correct_incomplete">
      <facetEntailment facetID="VB_42_f1" label="Assumed"/>
      <facetEntailment facetID="VB_42_f2" label="Inferred"/>
      <facetEntailment facetID="VB_42_f3" label="Expressed"/>
      <facetEntailment facetID="VB_42_f4" label="Expressed"/>
      <facetEntailment facetID="VB_42_f5" label="Diff-Arg"/>
      <facetEntailment facetID="VB_42_f6" label="Unaddressed"/>
      <facetEntailment facetID="VB_42_f7" label="Assumed"/>
      <facetEntailment facetID="VB_42_f8" label="Assumed"/>
      <facetEntailment facetID="VB_42_f9" label="Inferred"/>
    </studentAnswer>
    <studentAnswer id="VB.42.539.1" answerText="That will more number of blocks the slower it goes." accuracy="partially_correct_incomplete">
      <facetEntailment facetID="VB_42_f1" label="Assumed"/>
      <facetEntailment facetID="VB_42_f2" label="Unaddressed"/>
      <facetEntailment facetID="VB_42_f3" label="Expressed"/>
      <facetEntailment facetID="VB_42_f4" label="Expressed"/>
      <facetEntailment facetID="VB_42_f5" label="Diff-Arg"/>
      <facetEntailment facetID="VB_42_f6" label="Unaddressed"/>
      <facetEntailment facetID="VB_42_f7" label="Assumed"/>
      <facetEntailment facetID="VB_42_f8" label="Assumed"/>
      <facetEntailment facetID="VB_42_f9" label="Inferred"/>
    </studentAnswer>
    <studentAnswer id="VB.42.542.1" answerText="The distance of the meter is going lower. The number of blocks is going lower too." accuracy="contradictory">
      <facetEntailment facetID="VB_42_f1" label="Assumed"/>
      <facetEntailment facetID="VB_42_f2" label="Inferred"/>
      <facetEntailment facetID="VB_42_f3" label="Contra-Expr"/>
      <facetEntailment facetID="VB_42_f4" label="Assumed"/>
      <facetEntailment facetID="VB_42_f5" label="Inferred"/>
      <facetEntailment facetID="VB_42_f6" label="Expressed"/>
      <facetEntailment facetID="VB_42_f7" label="Assumed"/>
      <facetEntailment facetID="VB_42_f8" label="Assumed"/>
      <facetEntailment facetID="VB_42_f9" label="Expressed"/>
    </studentAnswer>
    <studentAnswer id="VB.42.545.1" answerText="The distance of the meter is going lower. Number of blocks is getting lower too." accuracy="contradictory">
      <facetEntailment facetID="VB_42_f1" label="Assumed"/>
      <facetEntailment facetID="VB_42_f2" label="Unaddressed"/>
      <facetEntailment facetID="VB_42_f3" label="Contra-Expr"/>
      <facetEntailment facetID="VB_42_f4" label="Assumed"/>
      <facetEntailment facetID="VB_42_f5" label="Unaddressed"/>
      <facetEntailment facetID="VB_42_f6" label="Expressed"/>
      <facetEntailment facetID="VB_42_f7" label="Assumed"/>
      <facetEntailment facetID="VB_42_f8" label="Assumed"/>
      <facetEntailment facetID="VB_42_f9" label="Unaddressed"/>
    </studentAnswer>
    <studentAnswer id="VB.42.626.1" answerText="The more blocks added the farther it went." accuracy="contradictory">
      <facetEntailment facetID="VB_42_f1" label="Assumed"/>
      <facetEntailment facetID="VB_42_f2" label="Expressed"/>
      <facetEntailment facetID="VB_42_f3" label="Expressed"/>
      <facetEntailment facetID="VB_42_f4" label="Expressed"/>
      <facetEntailment facetID="VB_42_f5" label="Contra-Expr"/>
      <facetEntailment facetID="VB_42_f6" label="Contra-Expr"/>
      <facetEntailment facetID="VB_42_f7" label="Assumed"/>
      <facetEntailment facetID="VB_42_f8" label="Assumed"/>
      <facetEntailment facetID="VB_42_f9" label="Expressed"/>
    </studentAnswer>
    <studentAnswer id="VB.42.632.1" answerText="The more blocks the less it goes." accuracy="correct">
      <facetEntailment facetID="VB_42_f1" label="Assumed"/>
      <facetEntailment facetID="VB_42_f2" label="Inferred"/>
      <facetEntailment facetID="VB_42_f3" label="Expressed"/>
      <facetEntailment facetID="VB_42_f4" label="Expressed"/>
      <facetEntailment facetID="VB_42_f5" label="Expressed"/>
      <facetEntailment facetID="VB_42_f6" label="Inferred"/>
      <facetEntailment facetID="VB_42_f7" label="Assumed"/>
      <facetEntailment facetID="VB_42_f8" label="Assumed"/>
      <facetEntailment facetID="VB_42_f9" label="Expressed"/>
    </studentAnswer>
    <studentAnswer id="VB.42.634.1" answerText="It goes up each one." accuracy="contradictory">
      <facetEntailment facetID="VB_42_f1" label="Assumed"/>
      <facetEntailment facetID="VB_42_f2" label="Unaddressed"/>
      <facetEntailment facetID="VB_42_f3" label="Inferred"/>
      <facetEntailment facetID="VB_42_f4" label="Assumed"/>
      <facetEntailment facetID="VB_42_f5" label="Contra-Infr"/>
      <facetEntailment facetID="VB_42_f6" label="Contra-Infr"/>
      <facetEntailment facetID="VB_42_f7" label="Assumed"/>
      <facetEntailment facetID="VB_42_f8" label="Assumed"/>
      <facetEntailment facetID="VB_42_f9" label="Inferred"/>
    </studentAnswer>
    <studentAnswer id="VB.42.636.1" answerText="The relationship is that each time he add a block it goes about one meter lower." accuracy="correct">
      <facetEntailment facetID="VB_42_f1" label="Assumed"/>
      <facetEntailment facetID="VB_42_f2" label="Expressed"/>
      <facetEntailment facetID="VB_42_f3" label="Expressed"/>
      <facetEntailment facetID="VB_42_f4" label="Expressed"/>
      <facetEntailment facetID="VB_42_f5" label="Expressed"/>
      <facetEntailment facetID="VB_42_f6" label="Expressed"/>
      <facetEntailment facetID="VB_42_f7" label="Assumed"/>
      <facetEntailment facetID="VB_42_f8" label="Assumed"/>
      <facetEntailment facetID="VB_42_f9" label="Expressed"/>
    </studentAnswer>
    <studentAnswer id="VB.42.638.1" answerText="The more blocks the less it will go." accuracy="correct">
      <facetEntailment facetID="VB_42_f1" label="Assumed"/>
      <facetEntailment facetID="VB_42_f2" label="Inferred"/>
      <facetEntailment facetID="VB_42_f3" label="Expressed"/>
      <facetEntailment facetID="VB_42_f4" label="Expressed"/>
      <facetEntailment facetID="VB_42_f5" label="Expressed"/>
      <facetEntailment facetID="VB_42_f6" label="Expressed"/>
      <facetEntailment facetID="VB_42_f7" label="Assumed"/>
      <facetEntailment facetID="VB_42_f8" label="Assumed"/>
      <facetEntailment facetID="VB_42_f9" label="Expressed"/>
    </studentAnswer>
    <studentAnswer id="VB.42.639.1" answerText="The more blocks it carried the less farther it would go." accuracy="correct">
      <facetEntailment facetID="VB_42_f1" label="Expressed"/>
      <facetEntailment facetID="VB_42_f2" label="Expressed"/>
      <facetEntailment facetID="VB_42_f3" label="Expressed"/>
      <facetEntailment facetID="VB_42_f4" label="Expressed"/>
      <facetEntailment facetID="VB_42_f5" label="Expressed"/>
      <facetEntailment facetID="VB_42_f6" label="Expressed"/>
      <facetEntailment facetID="VB_42_f7" label="Assumed"/>
      <facetEntailment facetID="VB_42_f8" label="Assumed"/>
      <facetEntailment facetID="VB_42_f9" label="Expressed"/>
    </studentAnswer>
    <studentAnswer id="VB.42.643.1" answerText="The more blocks the less meters it goes." accuracy="correct">
      <facetEntailment facetID="VB_42_f1" label="Assumed"/>
      <facetEntailment facetID="VB_42_f2" label="Inferred"/>
      <facetEntailment facetID="VB_42_f3" label="Expressed"/>
      <facetEntailment facetID="VB_42_f4" label="Expressed"/>
      <facetEntailment facetID="VB_42_f5" label="Expressed"/>
      <facetEntailment facetID="VB_42_f6" label="Expressed"/>
      <facetEntailment facetID="VB_42_f7" label="Assumed"/>
      <facetEntailment facetID="VB_42_f8" label="Assumed"/>
      <facetEntailment facetID="VB_42_f9" label="Expressed"/>
    </studentAnswer>
  </studentAnswers>
</question>
